Metadata-Version: 1.1
Name: logthis
Version: 1.0.1
Summary: a singleton, two-level, colorful, thread-safe, knob-free, logging library for in-house software
Home-page: https://github.com/Parquery/logthis
Author: Marko Ristin
Author-email: marko.ristin@parquery.com
License: MIT License
Keywords: logging log colorful color simple plain straightforward
Platform: UNKNOWN
Classifier: Development Status :: 5 - Production/Stable
Classifier: Intended Audience :: Developers
Classifier: License :: OSI Approved :: MIT License
Classifier: Programming Language :: Python :: 3.5
